bluesms/__init__.py
bluesms/config.py
bluesms/sms.py
bluesms/utils.py
bluesms-1.1.2.dist-info/AUTHORS.md
bluesms-1.1.2.dist-info/LICENSE
bluesms-1.1.2.dist-info/METADATA
bluesms-1.1.2.dist-info/WHEEL
bluesms-1.1.2.dist-info/top_level.txt
bluesms-1.1.2.dist-info/RECORD
