Metadata-Version: 2.1
Name: bluesms
Version: 1.1.2
Summary: A Python library for sending SMS messages via BlueSMS
Author: Mwanja Joel, Loyo Moses Victor
License: MIT License        
Project-URL: Homepage, https://github.com/mwanjajoel/bluesms
Keywords: sms,bluesms,python
Classifier: License :: OSI Approved :: MIT License
Classifier: Programming Language :: Python
Classifier: Programming Language :: Python :: 3
License-File: LICENSE
License-File: AUTHORS.md
